matchescu/blocking/__init__.py
matchescu/blocking/_block.py
matchescu/blocking/_blocker.py
matchescu/blocking/_blocking_metrics.py
matchescu/blocking/_lsh.py
matchescu/blocking/_sorted_neighborhood.py
matchescu/blocking/_tf_idf.py
matchescu/blocking/_tokenization.py
matchescu/comparison_filtering/__init__.py
matchescu/comparison_filtering/_filters.py
matchescu/csg/__init__.py
matchescu/csg/_binary_csg.py
matchescu/csg/_evaluator.py
matchescu_comparison_space_generation-0.7.2.dist-info/LICENSE
matchescu_comparison_space_generation-0.7.2.dist-info/METADATA
matchescu_comparison_space_generation-0.7.2.dist-info/WHEEL
matchescu_comparison_space_generation-0.7.2.dist-info/RECORD
