Metadata-Version: 2.1
Name: matchescu-comparison-space-generation
Version: 0.7.2
Summary: 
Author: Andrei Olar
Author-email: andrei.olar@samlex.ro
Requires-Python: >=3.12,<4.0
Classifier: Programming Language :: Python :: 3
Classifier: Programming Language :: Python :: 3.12
Classifier: Programming Language :: Python :: 3.13
Requires-Dist: datasketch (>=1.6.5,<2.0.0)
Requires-Dist: matchescu-base (>=0.22.1,<0.23.0)
Requires-Dist: matchescu-reference-store (>=0.8.3,<0.9.0)
Requires-Dist: numpy (>=2.2.4,<3.0.0)
Requires-Dist: scikit-learn (>=1.6.1,<2.0.0)
Requires-Dist: stopwords (>=1.0.1,<2.0.0)
